astra_latex_tools/__init__.py
astra_latex_tools/table_constructor.py
astra_latex_tools-0.1.0.dist-info/METADATA
astra_latex_tools-0.1.0.dist-info/WHEEL
astra_latex_tools-0.1.0.dist-info/RECORD
